forgeevent/__init__.py
forgeevent/py.typed
forgeevent/typing.py
forgeevent/handlers/__init__.py
forgeevent/handlers/base.py
forgeevent/handlers/local.py
forgeevent-0.1.2.dist-info/METADATA
forgeevent-0.1.2.dist-info/WHEEL
forgeevent-0.1.2.dist-info/licenses/LICENSE
forgeevent-0.1.2.dist-info/RECORD
