Metadata-Version: 2.4
Name: forgeevent
Version: 0.1.2
Summary: This is a Python library for event management and dispatching, designed to be simple, flexible, and extensible.
Project-URL: Homepage, https://landygg.github.io/forgeevent-py/
Project-URL: Repository, https://github.com/landygg/forgeevent-py
Project-URL: Documentation, https://landygg.github.io/forgeevent-py/
Author-email: devvolf <devvolf@xkforge.com>
License-File: LICENSE
Keywords: python
Classifier: Intended Audience :: Developers
Classifier: Programming Language :: Python
Classifier: Programming Language :: Python :: 3
Classifier: Programming Language :: Python :: 3.12
Classifier: Programming Language :: Python :: 3.13
Classifier: Topic :: Software Development :: Libraries :: Python Modules
Requires-Python: <4.0,>=3.12
